vlm_robot_agent/__init__.py
vlm_robot_agent/prompts/__init__.py
vlm_robot_agent/prompts/conversation_prompts.json
vlm_robot_agent/prompts/interaction_prompts.json
vlm_robot_agent/prompts/navigation_prompts.json
vlm_robot_agent/vlm_agent/__init__.py
vlm_robot_agent/vlm_agent/__inti__.py
vlm_robot_agent/vlm_agent/action_types.py
vlm_robot_agent/vlm_agent/actions.py
vlm_robot_agent/vlm_agent/agent.py
vlm_robot_agent/vlm_agent/conversation.py
vlm_robot_agent/vlm_agent/goal_manager.py
vlm_robot_agent/vlm_agent/memory.py
vlm_robot_agent/vlm_agent/perception.py
vlm_robot_agent/vlm_agent/planner.py
vlm_robot_agent/vlm_agent/state_tracker.py
vlm_robot_agent/vlm_agent/utils.py
vlm_robot_agent/vlm_agent/io/__init__.py
vlm_robot_agent/vlm_agent/io/speech_io.py
vlm_robot_agent/vlm_inference/inference.py
vlm_robot_agent-0.3.2.dist-info/licenses/LICENSE
vlm_robot_agent-0.3.2.dist-info/METADATA
vlm_robot_agent-0.3.2.dist-info/WHEEL
vlm_robot_agent-0.3.2.dist-info/top_level.txt
vlm_robot_agent-0.3.2.dist-info/RECORD
