Metadata-Version: 2.4
Name: vlm_robot_agent
Version: 0.3.2
Summary: Agente robótico basado en VLM que navega e interactúa con personas según objetivos visuales
Author-email: Edison Bejarano <edison.bejarano@upc.edu>
License: MIT
Project-URL: Homepage, https://github.com/EjbejaranosAI/vlm_robot_agent
Project-URL: Repository, https://github.com/EjbejaranosAI/vlm_robot_agent
Keywords: robotics,vlm,openai,navigation,interaction
Requires-Python: >=3.10
License-File: LICENSE
Requires-Dist: openai==1.78.1
Requires-Dist: opencv-python==4.11.0.86
Requires-Dist: pyyaml
Requires-Dist: python-dotenv<0.11,>=0.9.1
Requires-Dist: pillow==9.0.1
Requires-Dist: protobuf<5,>=4.25.3
Requires-Dist: numpy<1.27,>=1.24
Requires-Dist: scipy>=1.12
Requires-Dist: sounddevice==0.5.2
Requires-Dist: coqui-tts
Requires-Dist: openai-whisper==20240930
Dynamic: license-file
